.editorconfig
AUTHORS
CHANGES
LICENSE
MANIFEST.in
README.rst
babel.ini
pytest.ini
setup.cfg
setup.py
tox.ini
Flask_Security_Classic.egg-info/PKG-INFO
Flask_Security_Classic.egg-info/SOURCES.txt
Flask_Security_Classic.egg-info/dependency_links.txt
Flask_Security_Classic.egg-info/not-zip-safe
Flask_Security_Classic.egg-info/requires.txt
Flask_Security_Classic.egg-info/top_level.txt
artwork/logo-helmet.svg
docs/Makefile
docs/api.rst
docs/authors.rst
docs/changelog.rst
docs/conf.py
docs/configuration.rst
docs/contents.rst.inc
docs/customizing.rst
docs/features.rst
docs/index.rst
docs/models.rst
docs/quickstart.rst
docs/requirements.txt
docs/_static/logo-full.png
docs/_static/logo-helmet.png
docs/_templates/sidebarintro.html
docs/_templates/sidebarlogo.html
flask_security/__init__.py
flask_security/babel.py
flask_security/changeable.py
flask_security/cli.py
flask_security/confirmable.py
flask_security/core.py
flask_security/datastore.py
flask_security/decorators.py
flask_security/forms.py
flask_security/passwordless.py
flask_security/recoverable.py
flask_security/registerable.py
flask_security/script.py
flask_security/signals.py
flask_security/utils.py
flask_security/views.py
flask_security/templates/security/_macros.html
flask_security/templates/security/_menu.html
flask_security/templates/security/_messages.html
flask_security/templates/security/base.html
flask_security/templates/security/change_password.html
flask_security/templates/security/forgot_password.html
flask_security/templates/security/login_user.html
flask_security/templates/security/register_user.html
flask_security/templates/security/reset_password.html
flask_security/templates/security/send_confirmation.html
flask_security/templates/security/send_login.html
flask_security/templates/security/email/change_notice.html
flask_security/templates/security/email/change_notice.txt
flask_security/templates/security/email/confirmation_instructions.html
flask_security/templates/security/email/confirmation_instructions.txt
flask_security/templates/security/email/login_instructions.html
flask_security/templates/security/email/login_instructions.txt
flask_security/templates/security/email/reset_instructions.html
flask_security/templates/security/email/reset_instructions.txt
