Metadata-Version: 2.1
Name: Flask-Security-Classic
Version: 3.0.2
Summary: Simple security for Flask apps.
Home-page: https://github.com/jingz/flask-security
Author: Matt Wright
Author-email: matt@nobien.net
License: MIT
Keywords: flask security
Platform: any
Classifier: Environment :: Web Environment
Classifier: Intended Audience :: Developers
Classifier: License :: OSI Approved :: MIT License
Classifier: Operating System :: OS Independent
Classifier: Programming Language :: Python
Classifier: Topic :: Internet :: WWW/HTTP :: Dynamic Content
Classifier: Topic :: Software Development :: Libraries :: Python Modules
Classifier: Programming Language :: Python :: 3.6
Classifier: Programming Language :: Python :: 3.7
Classifier: Programming Language :: Python :: 3.8
Classifier: Programming Language :: Python :: Implementation :: CPython
Classifier: Programming Language :: Python :: Implementation :: PyPy
Classifier: Development Status :: 4 - Beta
Provides-Extra: docs
Provides-Extra: tests
Provides-Extra: all
